Metadata-Version: 2.1
Name: prodis
Version: 1.0
Summary: Gaussian and Binomial distributions
Author: Mizaid Ulises Ortega Ortega
Author-email: uliortegao@gmail.com
License: UNKNOWN
Platform: UNKNOWN
